{
    "en": {
        "title": "About me",
        "name": "Balazs Bencs",
        "image": "/images/me.jpeg",
        "description": "Experienced web programmer with a demonstrated history of working in a multinational industry, highly skilled in Artificial Intelligence, JavaScript variants, and Python. Learn and teach Extreme Programming and develop fully qualified code. He offten presents in many kinds of IT topics at the same time he investigates and shares the newest technologies with the community and his working teams.",
        "contactButtonText": "What can I do for you?",
        "cvButtonText": "Show CV",
        "contactButtonIcon": "fas fa-download",
        "cvButtonIcon": "fas fa-address-card"
    },
    "hu": {
        "title": "About me",
        "name": "Balazs Bencs",
        "image": "/images/me.jpeg",
        "description": "Tapasztalt <strong>Web fejlesztő</strong>, aki hosszú ideig dolgozott az oktatásban, majd az <strong>IBM ISSC</strong> fejlesztője lett. Erős tudása van a Hálózat üzemeltetés, a Moodle, SQL, PHP, JAVA, HTML5, CSS4 NodeJs, Angular, Drupal and WordPress technológiák használatában. Megbízható informatikai tudást szerzett a diplomával, ami különösen érvényes a  rendszer programozásra, a hálózatkezelésre, és a LAN/WAN Management-re.",
        "contactButtonText": "Miben tudok segíteni?",
        "cvButtonText": "CV mutatása",
        "contactButtonIcon": "fas fa-download",
        "cvButtonIcon": "fas fa-address-card"
    }
}